web3mc/__init__.py
web3mc/abi.py
web3mc/auto.py
web3mc/call.py
web3mc/constants.py
web3mc/exceptions.py
web3mc/multicall.py
web3mc-0.1.13.dist-info/LICENSE
web3mc-0.1.13.dist-info/METADATA
web3mc-0.1.13.dist-info/WHEEL
web3mc-0.1.13.dist-info/RECORD
