Metadata-Version: 2.1
Name: web3mc
Version: 0.1.13
Summary: Multicall library for aggregating web3py contract calls
Home-page: https://github.com/amfet42/web3mc
License: MIT
Keywords: web3,multicall
Author: amfet42
Requires-Python: >=3.10,<4.0
Classifier: License :: OSI Approved :: MIT License
Classifier: Programming Language :: Python :: 3
Classifier: Programming Language :: Python :: 3.10
Classifier: Programming Language :: Python :: 3.11
Requires-Dist: web3 (>=6.0.0)
Project-URL: Repository, https://github.com/amfet42/web3mc
